dgexcel/__init__.py
dgexcel/base.py
dgexcel/constants.py
dgexcel/excel.py
dgexcel/excel_x.py
dgexcel/utils.py
dgexcel-1.0.0a0.dist-info/licenses/LICENSE
dgexcel-1.0.0a0.dist-info/METADATA
dgexcel-1.0.0a0.dist-info/WHEEL
dgexcel-1.0.0a0.dist-info/top_level.txt
dgexcel-1.0.0a0.dist-info/RECORD
