Metadata-Version: 2.4
Name: dgexcel
Version: 1.0.0a0
Summary: Пакет для работы с Excel файлами
Home-page: https://gitlab.com/gng-group/dgdb.git
Author: Malanris
Author-email: Roman Rasputin <admin@roro.su>
License: MIT License
Project-URL: Homepage, https://gitlab.com/gng-group/dgexcel
Project-URL: BugTracker, https://gitlab.com/gng-group/dgexcel/issues
Keywords: sqlalchemy,client,postgresql,mssql,oracle
Classifier: Development Status :: 4 - Beta
Classifier: Intended Audience :: Developers
Classifier: License :: OSI Approved :: MIT License
Classifier: Programming Language :: Python :: 3.10
Classifier: Programming Language :: Python :: 3.11
Classifier: Programming Language :: Python :: 3.12
Classifier: Programming Language :: Python :: 3.13
Classifier: Operating System :: OS Independent
Classifier: Topic :: Software Development :: Libraries :: Python Modules
Classifier: Topic :: System :: Distributed Computing
Requires-Python: >=3.10
License-File: LICENSE
Requires-Dist: openpyxl>=3.0.0
Provides-Extra: xls
Requires-Dist: xlwt>=1.3.0; extra == "xls"
Requires-Dist: xlrd>=2.0.0; extra == "xls"
Provides-Extra: full
Requires-Dist: openpyxl>=3.0.0; extra == "full"
Requires-Dist: xlsxwriter>=3.0.0; extra == "full"
Requires-Dist: xlwt>=1.3.0; extra == "full"
Requires-Dist: xlrd>=2.0.0; extra == "full"
Dynamic: author
Dynamic: home-page
Dynamic: license-file
